setup.py
ydd.py
ydd.egg-info/PKG-INFO
ydd.egg-info/SOURCES.txt
ydd.egg-info/dependency_links.txt
ydd.egg-info/entry_points.txt
ydd.egg-info/not-zip-safe
ydd.egg-info/requires.txt
ydd.egg-info/top_level.txt