Metadata-Version: 1.0
Name: ydd
Version: 0.2
Summary: youdao dict terminal
Home-page: https://github.com/dengshilong/ydd
Author: dengshilong
Author-email: dengshilong1988@gmail.com
License: UNKNOWN
Keywords: youdao dict terminal
Platform: UNKNOWN
